miniduct/__init__.py
miniduct/datasources.py
miniduct/outputs.py
miniduct/pipeline.py
miniduct-0.2.6.dist-info/METADATA
miniduct-0.2.6.dist-info/WHEEL
miniduct-0.2.6.dist-info/RECORD
