Metadata-Version: 2.3
Name: miniduct
Version: 0.2.6
Summary: a small library for monothread orchestration of data pipelines
Keywords: miniduct,data-pipeline,data-processing
Author: watacoso
Author-email: watacoso@gmail.com
Requires-Python: >=3.12
Classifier: Programming Language :: Python :: 3
Classifier: Programming Language :: Python :: 3.12
Classifier: License :: OSI Approved :: MIT License
Classifier: Operating System :: OS Independent
Classifier: Development Status :: 1 - Planning
Classifier: Intended Audience :: Developers
Classifier: Topic :: Software Development :: Libraries
Requires-Dist: black (>=25.1.0,<26.0.0)
Requires-Dist: google-cloud-storage (>=3.1.1,<4.0.0)
Requires-Dist: pre-commit (>=4.2.0,<5.0.0)
Requires-Dist: requests (>=2.32.4,<3.0.0)
Requires-Dist: ruff (>=0.12.1,<0.13.0)
